odoo/addons/product_variant_available_in_pos/README.rst
odoo/addons/product_variant_available_in_pos/__init__.py
odoo/addons/product_variant_available_in_pos/__manifest__.py
odoo/addons/product_variant_available_in_pos/hooks.py
odoo/addons/product_variant_available_in_pos/i18n/ar.po
odoo/addons/product_variant_available_in_pos/i18n/ca.po
odoo/addons/product_variant_available_in_pos/i18n/de.po
odoo/addons/product_variant_available_in_pos/i18n/el_GR.po
odoo/addons/product_variant_available_in_pos/i18n/es.po
odoo/addons/product_variant_available_in_pos/i18n/es_ES.po
odoo/addons/product_variant_available_in_pos/i18n/es_MX.po
odoo/addons/product_variant_available_in_pos/i18n/eu.po
odoo/addons/product_variant_available_in_pos/i18n/fi.po
odoo/addons/product_variant_available_in_pos/i18n/fr.po
odoo/addons/product_variant_available_in_pos/i18n/fr_CH.po
odoo/addons/product_variant_available_in_pos/i18n/fr_FR.po
odoo/addons/product_variant_available_in_pos/i18n/gl.po
odoo/addons/product_variant_available_in_pos/i18n/hr.po
odoo/addons/product_variant_available_in_pos/i18n/hr_HR.po
odoo/addons/product_variant_available_in_pos/i18n/it.po
odoo/addons/product_variant_available_in_pos/i18n/nl.po
odoo/addons/product_variant_available_in_pos/i18n/nl_NL.po
odoo/addons/product_variant_available_in_pos/i18n/product_variant_available_in_pos.pot
odoo/addons/product_variant_available_in_pos/i18n/pt.po
odoo/addons/product_variant_available_in_pos/i18n/pt_BR.po
odoo/addons/product_variant_available_in_pos/i18n/ro.po
odoo/addons/product_variant_available_in_pos/i18n/ru.po
odoo/addons/product_variant_available_in_pos/i18n/sk.po
odoo/addons/product_variant_available_in_pos/i18n/sl.po
odoo/addons/product_variant_available_in_pos/i18n/tr.po
odoo/addons/product_variant_available_in_pos/i18n/tr_TR.po
odoo/addons/product_variant_available_in_pos/i18n/vi_VN.po
odoo/addons/product_variant_available_in_pos/i18n/zh_CN.po
odoo/addons/product_variant_available_in_pos/models/__init__.py
odoo11_addon_product_variant_available_in_pos-11.0.1.0.0.99.dev7.dist-info/METADATA
odoo11_addon_product_variant_available_in_pos-11.0.1.0.0.99.dev7.dist-info/WHEEL
odoo11_addon_product_variant_available_in_pos-11.0.1.0.0.99.dev7.dist-info/top_level.txt
odoo11_addon_product_variant_available_in_pos-11.0.1.0.0.99.dev7.dist-info/RECORD
